company/__init__.py
company/base_company.py
company/cli.py
company/version.py
company/data/drug_data.csv
company/medical/__init__.py
company/medical/medical.py
company_package-0.0.post4.dist-info/licenses/LICENSE
cpenv/bin/pwiz.py
company_package-0.0.post4.dist-info/METADATA
company_package-0.0.post4.dist-info/WHEEL
company_package-0.0.post4.dist-info/entry_points.txt
company_package-0.0.post4.dist-info/top_level.txt
company_package-0.0.post4.dist-info/RECORD
