Metadata-Version: 2.4
Name: company_package
Version: 0.0.post4
Summary: A Python package for modeling companies across various sectors.
Author-email: Your Name <your.email@example.com>, Boris <boris.bolliet@gmail.com>
License: MIT License
Project-URL: Documentation, https://your-readthedocs-url-here
Project-URL: Source, https://github.com/yourusername/companies_package
Project-URL: Issues, https://github.com/yourusername/companies_package/issues
Keywords: companies,finance,healthcare,technology
Classifier: Development Status :: 4 - Beta
Classifier: Intended Audience :: Information Technology
Classifier: License :: OSI Approved :: MIT License
Classifier: Programming Language :: Python :: 3
Classifier: Topic :: Software Development :: Libraries
Requires-Python: >=3.9
License-File: LICENSE
Requires-Dist: numpy
Requires-Dist: pandas
Requires-Dist: yfinance
Requires-Dist: argparse
Requires-Dist: datetime
Requires-Dist: importlib.resources
Dynamic: license-file
